LICENSE
README.md
setup.py
Spayk.egg-info/PKG-INFO
Spayk.egg-info/SOURCES.txt
Spayk.egg-info/dependency_links.txt
Spayk.egg-info/requires.txt
Spayk.egg-info/top_level.txt
spayk/Core.py
spayk/Learning.py
spayk/Models.py
spayk/Organization.py
spayk/Stimuli.py
spayk/Synapses.py
spayk/Utils.py
spayk/Visualization.py
spayk/__init__.py
spayk.egg-info/PKG-INFO
spayk.egg-info/SOURCES.txt
spayk.egg-info/dependency_links.txt
spayk.egg-info/requires.txt
spayk.egg-info/top_level.txt