Metadata-Version: 2.1
Name: Spayk
Version: 0.1.1
Summary: SPAYK: An environment for spiking neural network simulation
Home-page: https://github.com/aggelen/Spayk
Author: Aykut Görkem Gelen
Author-email: aggelen@outlook.com
License: BSD 3-clause
Classifier: Development Status :: 1 - Planning
Classifier: Intended Audience :: Science/Research
Classifier: Operating System :: POSIX :: Linux
Classifier: Programming Language :: Python :: 3.4
Classifier: Programming Language :: Python :: 3.5
License-File: LICENSE
